iqr_outlier/__inint__.py
iqr_outlier/detection.py
iqr_outlier/removal.py
iqr_outlier-0.1.5.dist-info/METADATA
iqr_outlier-0.1.5.dist-info/WHEEL
iqr_outlier-0.1.5.dist-info/top_level.txt
iqr_outlier-0.1.5.dist-info/RECORD
