Metadata-Version: 2.2
Name: iqr_outlier
Version: 0.1.5
Summary: A library to detect and remove outliers using IQR.
Home-page: https://github.com/abhi-2301-git/iqr_outlier
Author: Abhinav Masih
Author-email: abhnv.msh@gmail.com
Classifier: Programming Language :: Python :: 3
Classifier: License :: Public Domain
Classifier: Operating System :: OS Independent
Requires-Python: >=3.6
Requires-Dist: pandas
Requires-Dist: numpy
Dynamic: author
Dynamic: author-email
Dynamic: classifier
Dynamic: description
Dynamic: description-content-type
Dynamic: home-page
Dynamic: requires-dist
Dynamic: requires-python
Dynamic: summary
